jaal/__init__.py
jaal/jaal.py
jaal/layout.py
jaal/assets/dashboard.png
jaal/assets/favicon.ico
jaal/assets/jaal_color.gif
jaal/assets/jaal_filter.gif
jaal/assets/jaal_node_image.png
jaal/assets/jaal_search.gif
jaal/assets/jaal_size.gif
jaal/assets/logo.png
jaal/assets/tooltip.css
jaal/datasets/__init__.py
jaal/datasets/load_got.py
jaal/datasets/parse_dataframe.py
jaal/datasets/got/got_edge_df.csv
jaal/datasets/got/got_node_df.csv
jaal-0.1.9.dist-info/LICENSE
jaal-0.1.9.dist-info/METADATA
jaal-0.1.9.dist-info/WHEEL
jaal-0.1.9.dist-info/top_level.txt
jaal-0.1.9.dist-info/RECORD
