Metadata-Version: 2.1
Name: jaal
Version: 0.1.9
Summary: jaal - your interactive network visualizer dashboard
Home-page: https://github.com/imohitmayank/jaal
Author: Mohit Mayank
Author-email: mohitmayank1@gmail.com
License: UNKNOWN
Platform: UNKNOWN
Classifier: Programming Language :: Python :: 3
Classifier: License :: OSI Approved :: MIT License
Classifier: Operating System :: OS Independent
Requires-Python: >=3.6
Requires-Dist: dash>=1.19.0
Requires-Dist: visdcc>=0.0.40
Requires-Dist: pandas>=1.2.1
Requires-Dist: dash-core-components>=1.15.0
Requires-Dist: dash-html-components>=1.1.2
Requires-Dist: dash-bootstrap-components<1
